{
    "code": "STREAM_VALIDATED",
    "message": "Stream record is fetched",
    "data": [
        {
            "id": "691b2b6224f2af2c8dfdcc26",
            "name": "Ashtapailu Sports VS Omrchecker",
            "category_name": "Cricket",
            "tour_id": "691b29aafa673af67ab1731d",
            "tour_name": "Pune Olympia T20 2025",
            "match_no": "7",
            "match_status": 1,
            "is_stream": 1,
            "stream_caption": "Upcoming",
            "start_date": "2025-11-20",
            "start_date_time": "2025-11-20T03:30:00.000Z",
            "team_a": {
                "id": "691b289ffd87c2948fb4809f",
                "name": "Ashtapailu Sports",
                "short_name": "Ashtapailu Sports",
                "logo": "https://styxsports.b-cdn.net/styxsports-public/teams/1763387546871-36789704.webp"
            },
            "team_b": {
                "id": "691b2924fa673af67ab1731c",
                "name": "Omrchecker",
                "short_name": "Omrchecker",
                "logo": "https://styxsports.b-cdn.net/styxsports-public/teams/1763387682555-631716582.webp"
            },
            "logo": "https://styxsports.b-cdn.net/styxsports-public/matches/1763388256040-665580810.webp",
            "venue": "",
            "score_match_id": 0
        },
        {
            "id": "6915dd1afd87c2948fb4802e",
            "name": "Hobart Hurricanes Women VS Melbourne Renegades Women",
            "category_name": "Cricket",
            "tour_id": "69158efa24f2af2c8dfdcbe0",
            "tour_name": "Women's Big Bash League 2025",
            "match_no": "16",
            "match_status": 1,
            "is_stream": 1,
            "stream_caption": "Upcoming",
            "start_date": "2025-11-20",
            "start_date_time": "2025-11-20T04:10:00.000Z",
            "team_a": {
                "id": "67144f5f8a9eea3b43513353",
                "name": "Hobart Hurricanes Women",
                "short_name": "Hobart Hurricanes Women",
                "logo": "https://styxsports.b-cdn.net/styxsports-public/teams/1763039698954-30288296.webp"
            },
            "team_b": {
                "id": "671b00e6c2a91e9745b09cd7",
                "name": "Melbourne Renegades Women",
                "short_name": "Melbourne Renegades Women",
                "logo": "https://styxsports.b-cdn.net/styxsports-public/teams/1763039786954-625307340.webp"
            },
            "logo": "https://styxsports.b-cdn.net/styxsports-public/matches/1763040534465-446750609.webp",
            "venue": "North Sydney Oval ,Sydney",
            "score_match_id": 93014
        },
        {
            "id": "691b2b921ee3a0177bd6922f",
            "name": "Metro CC VS Sunny XI",
            "category_name": "Cricket",
            "tour_id": "691b29aafa673af67ab1731d",
            "tour_name": "Pune Olympia T20 2025",
            "match_no": "8",
            "match_status": 1,
            "is_stream": 1,
            "stream_caption": "Upcoming",
            "start_date": "2025-11-20",
            "start_date_time": "2025-11-20T07:30:00.000Z",
            "team_a": {
                "id": "691b28dafd87c2948fb480a0",
                "name": "Metro CC",
                "short_name": "Metro CC",
                "logo": "https://styxsports.b-cdn.net/styxsports-public/teams/1763387607871-976150940.webp"
            },
            "team_b": {
                "id": "691b28bd1ee3a0177bd6922d",
                "name": "Sunny XI",
                "short_name": "Sunny XI",
                "logo": "https://styxsports.b-cdn.net/styxsports-public/teams/1763387579228-2196450.webp"
            },
            "logo": "https://styxsports.b-cdn.net/styxsports-public/matches/1763388303493-486793931.webp",
            "venue": "",
            "score_match_id": 0
        },
        {
            "id": "6915dd62fa673af67ab172d9",
            "name": "Sydney Sixers Women VS Melbourne Star Women",
            "category_name": "Cricket",
            "tour_id": "69158efa24f2af2c8dfdcbe0",
            "tour_name": "Women's Big Bash League 2025",
            "match_no": "17",
            "match_status": 1,
            "is_stream": 1,
            "stream_caption": "Upcoming",
            "start_date": "2025-11-20",
            "start_date_time": "2025-11-20T07:40:00.000Z",
            "team_a": {
                "id": "671b0027c2a91e9745b09cd2",
                "name": "Sydney Sixers Women",
                "short_name": "Sydney Sixers Women",
                "logo": "https://styxsports.b-cdn.net/styxsports-public/teams/1763039722139-350568486.webp"
            },
            "team_b": {
                "id": "671b0081c2a91e9745b09cd4",
                "name": "Melbourne Star Women",
                "short_name": "Melbourne Star Women",
                "logo": "https://styxsports.b-cdn.net/styxsports-public/teams/1763039748698-7945466.webp"
            },
            "logo": "https://styxsports.b-cdn.net/styxsports-public/matches/1763040605727-553883596.webp",
            "venue": "North Sydney Oval ,Sydney",
            "score_match_id": 93015
        },
        {
            "id": "691b1a24fa673af67ab1731a",
            "name": "Royal Champs VS Deccan Gladiators",
            "category_name": "Cricket",
            "tour_id": "691b12aafd87c2948fb48099",
            "tour_name": "Abu Dhabi T10 League 2025",
            "match_no": "6",
            "match_status": 1,
            "is_stream": 1,
            "stream_caption": "Upcoming",
            "start_date": "2025-11-20",
            "start_date_time": "2025-11-20T11:00:00.000Z",
            "team_a": {
                "id": "691b1172fd87c2948fb48098",
                "name": "Royal Champs",
                "short_name": "Royal Champs",
                "logo": "https://styxsports.b-cdn.net/styxsports-public/teams/1763381615812-446875682.webp"
            },
            "team_b": {
                "id": "673da2c69b1fbcd9a5703b58",
                "name": "Deccan Gladiators",
                "short_name": "Deccan Gladiators",
                "logo": "https://styxsports.b-cdn.net/styxsports-public/teams/1763381953414-534042059.webp"
            },
            "logo": "https://styxsports.b-cdn.net/styxsports-public/matches/1763383840794-930666607.webp",
            "venue": "Sheikh Zayed Stadium ,Abu Dhabi",
            "score_match_id": 94460
        },
        {
            "id": "691b1a66fd87c2948fb4809c",
            "name": "U.A.E. Bulls VS Vista Riders",
            "category_name": "Cricket",
            "tour_id": "691b12aafd87c2948fb48099",
            "tour_name": "Abu Dhabi T10 League 2025",
            "match_no": "7",
            "match_status": 1,
            "is_stream": 1,
            "stream_caption": "Upcoming",
            "start_date": "2025-11-20",
            "start_date_time": "2025-11-20T13:45:00.000Z",
            "team_a": {
                "id": "691b11c124f2af2c8dfdcc21",
                "name": "U.A.E. Bulls",
                "short_name": "U.A.E. Bulls",
                "logo": "https://styxsports.b-cdn.net/styxsports-public/teams/1763381693116-698414405.webp"
            },
            "team_b": {
                "id": "691b119afa673af67ab17317",
                "name": "Vista Riders",
                "short_name": "Vista Riders",
                "logo": "https://styxsports.b-cdn.net/styxsports-public/teams/1763381654137-638920004.webp"
            },
            "logo": "https://styxsports.b-cdn.net/styxsports-public/matches/1763383902325-836970266.webp",
            "venue": "Sheikh Zayed Stadium ,Abu Dhabi",
            "score_match_id": 94461
        },
        {
            "id": "691b1a8dfd87c2948fb4809d",
            "name": "Aspin Stallions VS Ajman Titans",
            "category_name": "Cricket",
            "tour_id": "691b12aafd87c2948fb48099",
            "tour_name": "Abu Dhabi T10 League 2025",
            "match_no": "8",
            "match_status": 1,
            "is_stream": 1,
            "stream_caption": "Upcoming",
            "start_date": "2025-11-20",
            "start_date_time": "2025-11-20T16:00:00.000Z",
            "team_a": {
                "id": "691b10d2fd87c2948fb48097",
                "name": "Aspin Stallions",
                "short_name": "Aspin Stallions",
                "logo": "https://styxsports.b-cdn.net/styxsports-public/teams/1763381431526-154194744.webp"
            },
            "team_b": {
                "id": "691b10ac1ee3a0177bd69227",
                "name": "Ajman Titans",
                "short_name": "Ajman Titans",
                "logo": "https://styxsports.b-cdn.net/styxsports-public/teams/1763381418755-615007395.webp"
            },
            "logo": "https://styxsports.b-cdn.net/styxsports-public/matches/1763383946323-275015219.webp",
            "venue": "Sheikh Zayed Stadium ,Abu Dhabi",
            "score_match_id": 94462
        },
        {
            "id": "6917304424f2af2c8dfdcc03",
            "name": "Wellington Firebirds VS Otago",
            "category_name": "Cricket",
            "tour_id": "69172ea61ee3a0177bd69208",
            "tour_name": "Plunket Shield 2025",
            "match_no": "Match - 2 | Day 4",
            "match_status": 1,
            "is_stream": 1,
            "stream_caption": "Upcoming",
            "start_date": "2025-11-20",
            "start_date_time": "2025-11-20T21:00:00.000Z",
            "team_a": {
                "id": "68fa02b64e4aa6d729f67551",
                "name": "Wellington Firebirds",
                "short_name": "Wellington Firebirds",
                "logo": "https://styxsports.b-cdn.net/styxsports-public/teams/1761215154358-181406737.webp"
            },
            "team_b": {
                "id": "6916fc9224f2af2c8dfdcbfc",
                "name": "Otago",
                "short_name": "Otago",
                "logo": "https://styxsports.b-cdn.net/styxsports-public/teams/1763114127192-222904853.webp"
            },
            "logo": "https://styxsports.b-cdn.net/styxsports-public/matches/1763127357086-541756390.webp",
            "venue": "Basin Reserve ,Wellington",
            "score_match_id": 92902
        },
        {
            "id": "69173083fd87c2948fb48047",
            "name": "Canterbury Kings VS Northern District",
            "category_name": "Cricket",
            "tour_id": "69172ea61ee3a0177bd69208",
            "tour_name": "Plunket Shield 2025",
            "match_no": "Match - 3 | Day 4",
            "match_status": 1,
            "is_stream": 1,
            "stream_caption": "Upcoming",
            "start_date": "2025-11-20",
            "start_date_time": "2025-11-20T21:00:00.000Z",
            "team_a": {
                "id": "68fa0386f77cf099f802bdba",
                "name": "Canterbury Kings",
                "short_name": "Canterbury Kings",
                "logo": "https://styxsports.b-cdn.net/styxsports-public/teams/1761215195169-291451803.webp"
            },
            "team_b": {
                "id": "68fa04135e14fc3d2e06974a",
                "name": "Northern District",
                "short_name": "Northern District",
                "logo": "https://styxsports.b-cdn.net/styxsports-public/teams/1761215501300-267603040.webp"
            },
            "logo": "https://styxsports.b-cdn.net/styxsports-public/matches/1763127424056-136599788.webp",
            "venue": "Mainpower Oval (Recreation Ground) ,Rangiora",
            "score_match_id": 92903
        }
    ]
}